algolearn/__init__.py
algolearn/multiplication.py
algolearn-0.1.0.dist-info/LICENSE
algolearn-0.1.0.dist-info/METADATA
algolearn-0.1.0.dist-info/WHEEL
algolearn-0.1.0.dist-info/top_level.txt
algolearn-0.1.0.dist-info/RECORD
