Metadata-Version: 2.1
Name: algolearn
Version: 0.1.0
Summary: Custom implementation of standard library to help learn Data Structures, Algorithms and Leetcode
Home-page: https://algolearn.readthedocs.io/
Author: Liam Esteban Prince
Author-email: liamesteban@gmail.com
License: MIT
Classifier: Intended Audience :: Developers
Classifier: License :: OSI Approved :: MIT License
Classifier: Programming Language :: Python
Classifier: Programming Language :: Python :: 3
Classifier: Programming Language :: Python :: 3.6
Classifier: Programming Language :: Python :: 3.7
Classifier: Programming Language :: Python :: 3.8
Classifier: Programming Language :: Python :: 3.9
Classifier: Operating System :: OS Independent
License-File: LICENSE
